managed_mac_utils/__init__.py
managed_mac_utils/managed_mac_utils.py
ucam_managed_mac_utils-0.0.4.dist-info/LICENSE
ucam_managed_mac_utils-0.0.4.dist-info/METADATA
ucam_managed_mac_utils-0.0.4.dist-info/WHEEL
ucam_managed_mac_utils-0.0.4.dist-info/top_level.txt
ucam_managed_mac_utils-0.0.4.dist-info/RECORD
