Metadata-Version: 2.1
Name: ucam-managed-mac-utils
Version: 0.0.4
Summary: A collection of useful functions for managing Macs at University of Cambridge
Home-page: https://gitlab.developers.cam.ac.uk/uis/desktopsystems/ucam_managed_mac_utils.git
Author: James Nairn
Author-email: jwrn3@cam.ac.uk
License: UNKNOWN
Platform: UNKNOWN
Classifier: Programming Language :: Python :: 3
Classifier: License :: OSI Approved :: MIT License
Requires-Dist: pyobjc
